LICENSE
MANIFEST.in
README.md
setup.cfg
setup.py
cuda/bincount.cpp
cuda/bincount_kernel.cu
test/__init__.py
test/test_bincount.py
test/utils.py
torch_bincount/__init__.py
torch_bincount/bincount.py
torch_bincount.egg-info/PKG-INFO
torch_bincount.egg-info/SOURCES.txt
torch_bincount.egg-info/dependency_links.txt
torch_bincount.egg-info/requires.txt
torch_bincount.egg-info/top_level.txt