Metadata-Version: 1.1
Name: torch-bincount
Version: 0.1.1
Summary: Optimized PyTorch BinCount Operation
Home-page: https://github.com/rusty1s/pytorch_bincount
Author: Matthias Fey
Author-email: matthias.fey@tu-dortmund.de
License: UNKNOWN
Download-URL: https://github.com/rusty1s/pytorch_bincount/archive/0.1.1.tar.gz
Keywords: pytorch,bincount,python
Platform: UNKNOWN
